deamstools/__init__.py
deamstools/tools.py
deamstools-1.3.0.dist-info/licenses/LICENSE
deamstools-1.3.0.dist-info/METADATA
deamstools-1.3.0.dist-info/WHEEL
deamstools-1.3.0.dist-info/entry_points.txt
deamstools-1.3.0.dist-info/top_level.txt
deamstools-1.3.0.dist-info/RECORD
