Metadata-Version: 2.4
Name: deamstools
Version: 1.3.0
Summary: A Few Tools i made for my self. You can use them too!
Author: DEAMJAVA
Author-email: deamminecraft3@gmail.com
Requires-Python: >=3.12
License-File: LICENSE
Requires-Dist: packaging
Dynamic: author
Dynamic: author-email
Dynamic: license-file
Dynamic: requires-dist
Dynamic: requires-python
Dynamic: summary
